iWAN/__init__.py
iWAN/iWAN.py
iWAN-0.0.3.dist-info/METADATA
iWAN-0.0.3.dist-info/WHEEL
iWAN-0.0.3.dist-info/top_level.txt
iWAN-0.0.3.dist-info/RECORD
