Metadata-Version: 2.1
Name: iWAN
Version: 0.0.3
Summary: simple tool
Home-page: https://github.com/Nevquit/iWAN
Author: vSir
Author-email: weiguo341@gmail.com
Classifier: Programming Language :: Python :: 3
Classifier: License :: OSI Approved :: MIT License
Classifier: Operating System :: OS Independent
Requires-Dist: websocket-client (==0.58.0)
